// 
// Decompiled by Procyon v0.6.0
// 

package me.pi3ro.cuy.network;

import java.nio.charset.StandardCharsets;
import java.util.Random;
import java.io.IOException;
import kotlin.jvm.internal.Intrinsics;
import dbjrsyajbkgezbtp.ogwwobatgayyjyld;
import org.jetbrains.annotations.NotNull;
import java.util.HashMap;
import kotlin.Metadata;
import java.net.URLClassLoader;

@Metadata(mv = { 2, 2, 0 }, k = 1, xi = 48, d1 = { """
                                                   \u0000.
                                                   \u0002\u0018\u0002
                                                   \u0002\u0018\u0002
                                                   \u0000
                                                   \u0002\u0010\u0012
                                                   \u0000
                                                   \u0002\u0018\u0002
                                                   \u0002\b\u0003
                                                   \u0002\u0018\u0002
                                                   \u0002\u0010\u000e
                                                   \u0002\u0018\u0002
                                                   \u0000
                                                   \u0002\u0018\u0002
                                                   \u0002\b\u0003\u0018\u00002\u00020\u0001B\u0017\u0012\u0006\u0010\u0002\u001a\u00020\u0003\u0012\u0006\u0010\u0004\u001a\u00020\u0005¢\u0006\u0004\b\u0006\u0010\u0007J\u0014\u0010\f\u001a\u0006\u0012\u0002\b\u00030\r2\u0006\u0010\u000e\u001a\u00020
                                                   H\u0014J\u0012\u0010\u000f\u001a\u0006\u0012\u0002\b\u00030\r2\u0006\u0010\u000e\u001a\u00020
                                                   R*\u0010\b\u001a\u001e\u0012\u0004\u0012\u00020
                                                   \u0012\u0004\u0012\u00020\u00030	j\u000e\u0012\u0004\u0012\u00020
                                                   \u0012\u0004\u0012\u00020\u0003`\u000bX\u0082\u0004¢\u0006\u0002
                                                   \u0000¨\u0006\u0010""" }, d2 = { "Lme/pi3ro/cuy/network/ByteClassLoader;", "Ljava/net/URLClassLoader;", "jarBytes", "", "parent", "Ljava/lang/ClassLoader;", "<init>", "([BLjava/lang/ClassLoader;)V", "classBytes", "Ljava/util/HashMap;", "", "Lkotlin/collections/HashMap;", "findClass", "Ljava/lang/Class;", "name", "loadClassPublic", "cuy-plugin" })
public final class ByteClassLoader extends URLClassLoader
{
    @NotNull
    private final HashMap<String, byte[]> classBytes;
    private static int 5raxzV3R39 = 0;
    private transient int H5whZP3nQ9 = 1034028941;
    private static String[] nothing_to_see_here;
    
    public ByteClassLoader(@NotNull final byte[] p0, @NotNull final ClassLoader p1, final int p2) {
        // 
        // This method could not be decompiled.
        // 
        // Original Bytecode:
        // 
        //     2: ldc             293292330
        //     4: ixor           
        //     5: istore          104
        //     7: aload_1        
        //     8: astore          4
        //    10: ldc             "jarBytes"
        //    12: astore          5
        //    14: aload           4
        //    16: aload           5
        //    18: invokestatic    kotlin/jvm/internal/Intrinsics.checkNotNullParameter:(Ljava/lang/Object;Ljava/lang/String;)V
        //    21: aload_2        
        //    22: astore          20
        //    24: ldc             "parent"
        //    26: astore          71
        //    28: aload           20
        //    30: aload           71
        //    32: invokestatic    kotlin/jvm/internal/Intrinsics.checkNotNullParameter:(Ljava/lang/Object;Ljava/lang/String;)V
        //    35: ldc             1400604512
        //    37: ldc             701069711
        //    39: ixor           
        //    40: istore          104
        //    42: aload_0        
        //    43: astore          21
        //    45: iconst_0       
        //    46: istore          72
        //    48: iload           72
        //    50: anewarray       Ljava/net/URL;
        //    53: astore          73
        //    55: aload_2        
        //    56: astore          6
        //    58: aload           21
        //    60: aload           73
        //    62: aload           6
        //    64: invokespecial   java/net/URLClassLoader.<init>:([Ljava/net/URL;Ljava/lang/ClassLoader;)V
        //    67: iload           104
        //    69: invokestatic    dbjrsyajbkgezbtp/ogwwobatgayyjyld.yphcfoidvruxcacx:(I)I
        //    72: lookupswitch {
        //          230340445: 116
        //          1625017216: 67
        //          1723696531: 123
        //          1774039207: 3330
        //          default: 3330
        //        }
        //   116: ldc             1311504244
        //   118: iload           104
        //   120: ixor           
        //   121: istore          104
        //   123: ldc             828964941
        //   125: ldc             557317173
        //   127: ldc             "617084387"
        //   129: invokestatic    java/lang/Integer.parseInt:(Ljava/lang/String;)I
        //   132: ixor           
        //   133: ixor           
        //   134: istore          104
        //   136: aload_0        
        //   137: ldc             1034028941
        //   139: getstatic       me/pi3ro/cuy/network/ByteClassLoader.5raxzV3R39:I
        //   142: ixor           
        //   143: putfield        me/pi3ro/cuy/network/ByteClassLoader.H5whZP3nQ9:I
        //   146: iload           104
        //   148: ldc             617254176
        //   150: invokestatic    me/pi3ro/cuy/network/ByteClassLoader.ojfurpnnjakpinoa:(II)I
        //   153: istore          104
        //   155: ldc             42498773
        //   157: iload           104
        //   159: ixor           
        //   160: istore          104
        //   162: aload_0        
        //   163: astore          22
        //   165: new             Ljava/util/HashMap;
        //   168: astore          74
        //   170: aload           74
        //   172: invokespecial   java/util/HashMap.<init>:()V
        //   175: aload           22
        //   177: aload           74
        //   179: putfield        me/pi3ro/cuy/network/ByteClassLoader.classBytes:Ljava/util/HashMap;
        //   182: ldc             979164635
        //   184: iload           104
        //   186: ixor           
        //   187: istore          104
        //   189: ldc             51859374
        //   191: iload           104
        //   193: ixor           
        //   194: istore          104
        //   196: ldc             1665338686
        //   198: iload           104
        //   200: ixor           
        //   201: istore          104
        //   203: new             Ljava/io/ByteArrayInputStream;
        //   206: astore          23
        //   208: aload_1        
        //   209: astore          84
        //   211: aload           23
        //   213: aload           84
        //   215: invokespecial   java/io/ByteArrayInputStream.<init>:([B)V
        //   218: aload           23
        //   220: checkcast       Ljava/io/Closeable;
        //   223: astore          24
        //   225: aload           24
        //   227: astore          10
        //   229: aconst_null    
        //   230: astore          25
        //   232: aload           25
        //   234: astore          11
        //   236: ldc             322247382
        //   238: iload           104
        //   240: ixor           
        //   241: istore          104
        //   243: aload           10
        //   245: astore          26
        //   247: aload           26
        //   249: checkcast       Ljava/io/ByteArrayInputStream;
        //   252: astore          27
        //   254: aload           27
        //   256: astore          12
        //   258: ldc             732227748
        //   260: iload           104
        //   262: ixor           
        //   263: istore          104
        //   265: iconst_0       
        //   266: istore          28
        //   268: iload           28
        //   270: istore          13
        //   272: ldc             2081820863
        //   274: iload           104
        //   276: ixor           
        //   277: istore          104
        //   279: new             Ljava/util/jar/JarInputStream;
        //   282: astore          29
        //   284: aload           12
        //   286: astore          85
        //   288: aload           85
        //   290: checkcast       Ljava/io/InputStream;
        //   293: astore          86
        //   295: aload           29
        //   297: aload           86
        //   299: invokespecial   java/util/jar/JarInputStream.<init>:(Ljava/io/InputStream;)V
        //   302: aload           29
        //   304: checkcast       Ljava/io/Closeable;
        //   307: astore          30
        //   309: aload           30
        //   311: astore          14
        //   313: aconst_null    
        //   314: astore          31
        //   316: aload           31
        //   318: astore          15
        //   320: ldc             1527429081
        //   322: iload           104
        //   324: ixor           
        //   325: istore          104
        //   327: aload           14
        //   329: astore          32
        //   331: aload           32
        //   333: checkcast       Ljava/util/jar/JarInputStream;
        //   336: astore          33
        //   338: aload           33
        //   340: astore          16
        //   342: ldc             39398638
        //   344: iload           104
        //   346: ixor           
        //   347: istore          104
        //   349: iconst_0       
        //   350: istore          34
        //   352: iload           34
        //   354: istore          17
        //   356: ldc             325109836
        //   358: iload           104
        //   360: ixor           
        //   361: istore          104
        //   363: aload           16
        //   365: astore          35
        //   367: aload           35
        //   369: invokevirtual   java/util/jar/JarInputStream.getNextJarEntry:()Ljava/util/jar/JarEntry;
        //   372: astore          36
        //   374: aload           36
        //   376: astore          18
        //   378: ldc             1687712645
        //   380: iload           104
        //   382: ixor           
        //   383: istore          104
        //   385: aload           18
        //   387: astore          37
        //   389: aload           37
        //   391: ifnull          1364
        //   394: ldc             1654482385
        //   396: iload           104
        //   398: ixor           
        //   399: istore          104
        //   401: aload           18
        //   403: astore          56
        //   405: aload           56
        //   407: invokevirtual   java/util/jar/JarEntry.isDirectory:()Z
        //   410: istore          57
        //   412: iload           57
        //   414: ifne            907
        //   417: ldc             1110966699
        //   419: iload           104
        //   421: ixor           
        //   422: istore          104
        //   424: aload           18
        //   426: astore          58
        //   428: aload           58
        //   430: invokevirtual   java/util/jar/JarEntry.getName:()Ljava/lang/String;
        //   433: astore          59
        //   435: ldc             "getName(...)"
        //   437: astore          87
        //   439: aload           59
        //   441: aload           87
        //   443: invokestatic    kotlin/jvm/internal/Intrinsics.checkNotNullExpressionValue:(Ljava/lang/Object;Ljava/lang/String;)V
        //   446: ldc             ".class"
        //   448: astore          79
        //   450: iconst_0       
        //   451: istore          88
        //   453: iconst_2       
        //   454: istore          7
        //   456: aconst_null    
        //   457: astore          8
        //   459: aload           59
        //   461: aload           79
        //   463: iload           88
        //   465: iload           7
        //   467: aload           8
        //   469: invokestatic    kotlin/text/StringsKt.endsWith$default:(Ljava/lang/String;Ljava/lang/String;ZILjava/lang/Object;)Z
        //   472: istore          60
        //   474: iload           60
        //   476: ifeq            2067
        //   479: ldc             545898549
        //   481: iload           104
        //   483: ixor           
        //   484: istore          104
        //   486: aload           18
        //   488: astore          61
        //   490: aload           61
        //   492: invokevirtual   java/util/jar/JarEntry.getName:()Ljava/lang/String;
        //   495: astore          62
        //   497: ldc             "getName(...)"
        //   499: astore          89
        //   501: aload           62
        //   503: aload           89
        //   505: invokestatic    kotlin/jvm/internal/Intrinsics.checkNotNullExpressionValue:(Ljava/lang/Object;Ljava/lang/String;)V
        //   508: ldc             "/"
        //   510: astore          80
        //   512: ldc             "."
        //   514: astore          90
        //   516: iconst_0       
        //   517: istore          94
        //   519: iconst_4       
        //   520: istore          95
        //   522: aconst_null    
        //   523: astore          9
        //   525: aload           62
        //   527: aload           80
        //   529: aload           90
        //   531: iload           94
        //   533: iload           95
        //   535: aload           9
        //   537: invokestatic    kotlin/text/StringsKt.replace$default:(Ljava/lang/String;Ljava/lang/String;Ljava/lang/String;ZILjava/lang/Object;)Ljava/lang/String;
        //   540: astore          63
        //   542: ldc             ".class"
        //   544: astore          81
        //   546: aload           81
        //   548: checkcast       Ljava/lang/CharSequence;
        //   551: astore          82
        //   553: aload           63
        //   555: aload           82
        //   557: invokestatic    kotlin/text/StringsKt.removeSuffix:(Ljava/lang/String;Ljava/lang/CharSequence;)Ljava/lang/String;
        //   560: astore          64
        //   562: aload           64
        //   564: astore          19
        //   566: ldc             1310908221
        //   568: iload           104
        //   570: ixor           
        //   571: istore          104
        //   573: aload_0        
        //   574: astore          65
        //   576: aload           65
        //   578: getfield        me/pi3ro/cuy/network/ByteClassLoader.classBytes:Ljava/util/HashMap;
        //   581: astore          66
        //   583: aload           66
        //   585: checkcast       Ljava/util/Map;
        //   588: astore          67
        //   590: aload           19
        //   592: astore          83
        //   594: aload           16
        //   596: astore          91
        //   598: aload           91
        //   600: checkcast       Ljava/io/InputStream;
        //   603: astore          92
        //   605: aload           92
        //   607: invokestatic    kotlin/io/ByteStreamsKt.readBytes:(Ljava/io/InputStream;)[B
        //   610: astore          93
        //   612: aload           67
        //   614: aload           83
        //   616: aload           93
        //   618: invokeinterface java/util/Map.put:(Ljava/lang/Object;Ljava/lang/Object;)Ljava/lang/Object;
        //   623: astore          68
        //   625: ldc             953205088
        //   627: iload           104
        //   629: ixor           
        //   630: istore          104
        //   632: aload           16
        //   634: astore          69
        //   636: aload           69
        //   638: invokevirtual   java/util/jar/JarInputStream.getNextJarEntry:()Ljava/util/jar/JarEntry;
        //   641: astore          70
        //   643: aload           70
        //   645: astore          18
        //   647: goto            2008
        //   650: ldc             843704427
        //   652: iload           104
        //   654: ixor           
        //   655: istore          104
        //   657: getstatic       kotlin/Unit.INSTANCE:Lkotlin/Unit;
        //   660: astore          38
        //   662: ldc             1784438118
        //   664: iload           104
        //   666: ixor           
        //   667: istore          104
        //   669: aload           38
        //   671: astore          100
        //   673: ldc             1866103847
        //   675: iload           104
        //   677: ixor           
        //   678: istore          104
        //   680: aload           14
        //   682: astore          39
        //   684: aload           15
        //   686: astore          75
        //   688: aload           39
        //   690: aload           75
        //   692: invokestatic    kotlin/io/CloseableKt.closeFinally:(Ljava/io/Closeable;Ljava/lang/Throwable;)V
        //   695: goto            1374
        //   698: astore          50
        //   700: aload           50
        //   702: astore          101
        //   704: aload           101
        //   706: astore          51
        //   708: ldc             1237446162
        //   710: iload           104
        //   712: ixor           
        //   713: istore          104
        //   715: aload           51
        //   717: astore          15
        //   719: aload           101
        //   721: astore          52
        //   723: aload           52
        //   725: athrow         
        //   726: astore          53
        //   728: aload           53
        //   730: astore          102
        //   732: ldc             447008692
        //   734: iload           104
        //   736: ixor           
        //   737: istore          104
        //   739: aload           14
        //   741: astore          54
        //   743: aload           15
        //   745: astore          78
        //   747: aload           54
        //   749: aload           78
        //   751: invokestatic    kotlin/io/CloseableKt.closeFinally:(Ljava/io/Closeable;Ljava/lang/Throwable;)V
        //   754: aload           102
        //   756: astore          55
        //   758: aload           55
        //   760: athrow         
        //   761: ldc             1082348280
        //   763: iload           104
        //   765: ixor           
        //   766: istore          104
        //   768: getstatic       kotlin/Unit.INSTANCE:Lkotlin/Unit;
        //   771: astore          40
        //   773: ldc             1601157354
        //   775: iload           104
        //   777: ixor           
        //   778: istore          104
        //   780: aload           40
        //   782: astore          97
        //   784: ldc             1205409874
        //   786: iload           104
        //   788: ixor           
        //   789: istore          104
        //   791: aload           10
        //   793: astore          41
        //   795: aload           11
        //   797: astore          76
        //   799: aload           41
        //   801: aload           76
        //   803: invokestatic    kotlin/io/CloseableKt.closeFinally:(Ljava/io/Closeable;Ljava/lang/Throwable;)V
        //   806: goto            3178
        //   809: astore          44
        //   811: aload           44
        //   813: astore          98
        //   815: aload           98
        //   817: astore          45
        //   819: ldc             357670822
        //   821: iload           104
        //   823: ixor           
        //   824: istore          104
        //   826: aload           45
        //   828: astore          11
        //   830: aload           98
        //   832: astore          46
        //   834: aload           46
        //   836: athrow         
        //   837: astore          47
        //   839: aload           47
        //   841: astore          99
        //   843: ldc             1494626712
        //   845: iload           104
        //   847: ixor           
        //   848: istore          104
        //   850: aload           10
        //   852: astore          48
        //   854: aload           11
        //   856: astore          77
        //   858: aload           48
        //   860: aload           77
        //   862: invokestatic    kotlin/io/CloseableKt.closeFinally:(Ljava/io/Closeable;Ljava/lang/Throwable;)V
        //   865: aload           99
        //   867: astore          49
        //   869: aload           49
        //   871: athrow         
        //   872: iload           104
        //   874: invokestatic    dbjrsyajbkgezbtp/ogwwobatgayyjyld.gicktsuzorogcxcs:(I)I
        //   877: tableswitch {
        //          -745535504: 896
        //          default: 2539
        //        }
        //   896: iload           104
        //   898: iconst_0       
        //   899: invokestatic    me/pi3ro/cuy/network/ByteClassLoader.ojfurpnnjakpinoa:(II)I
        //   902: istore          104
        //   904: goto            726
        //   907: ldc             339992515
        //   909: iload           104
        //   911: ixor           
        //   912: istore          104
        //   914: goto            632
        //   917: iload           104
        //   919: invokestatic    dbjrsyajbkgezbtp/ogwwobatgayyjyld.gicktsuzorogcxcs:(I)I
        //   922: lookupswitch {
        //          -2112578885: 1332
        //          -1850429573: 1152
        //          -1593259998: 1140
        //          -1472674054: 1256
        //          -1165646477: 1236
        //          -1158569590: 1172
        //          -1137781653: 1116
        //          -1017756600: 1298
        //          -740696542: 1246
        //          -550248550: 1128
        //          -372767752: 1226
        //          -232676103: 1266
        //          51787322: 1288
        //          66841634: 1310
        //          316029792: 1216
        //          379075273: 1278
        //          402462897: 1354
        //          681843056: 1184
        //          750685874: 1194
        //          859735194: 1206
        //          1022262872: 1162
        //          1654923072: 1322
        //          1737409315: 1344
        //          default: 3167
        //        }
        //  1116: iload           104
        //  1118: ldc             826711937
        //  1120: invokestatic    me/pi3ro/cuy/network/ByteClassLoader.ojfurpnnjakpinoa:(II)I
        //  1123: istore          104
        //  1125: goto            809
        //  1128: iload           104
        //  1130: ldc             488980223
        //  1132: invokestatic    me/pi3ro/cuy/network/ByteClassLoader.ojfurpnnjakpinoa:(II)I
        //  1135: istore          104
        //  1137: goto            809
        //  1140: iload           104
        //  1142: ldc             316824584
        //  1144: invokestatic    me/pi3ro/cuy/network/ByteClassLoader.ojfurpnnjakpinoa:(II)I
        //  1147: istore          104
        //  1149: goto            809
        //  1152: ldc             888525027
        //  1154: iload           104
        //  1156: ixor           
        //  1157: istore          104
        //  1159: goto            809
        //  1162: ldc             1096714951
        //  1164: iload           104
        //  1166: ixor           
        //  1167: istore          104
        //  1169: goto            809
        //  1172: iload           104
        //  1174: ldc             295530813
        //  1176: invokestatic    me/pi3ro/cuy/network/ByteClassLoader.ojfurpnnjakpinoa:(II)I
        //  1179: istore          104
        //  1181: goto            809
        //  1184: ldc             1138214434
        //  1186: iload           104
        //  1188: ixor           
        //  1189: istore          104
        //  1191: goto            809
        //  1194: iload           104
        //  1196: ldc             55874778
        //  1198: invokestatic    me/pi3ro/cuy/network/ByteClassLoader.ojfurpnnjakpinoa:(II)I
        //  1201: istore          104
        //  1203: goto            809
        //  1206: ldc             10786207
        //  1208: iload           104
        //  1210: ixor           
        //  1211: istore          104
        //  1213: goto            809
        //  1216: ldc             1150911072
        //  1218: iload           104
        //  1220: ixor           
        //  1221: istore          104
        //  1223: goto            809
        //  1226: ldc             1543128435
        //  1228: iload           104
        //  1230: ixor           
        //  1231: istore          104
        //  1233: goto            809
        //  1236: ldc             831779234
        //  1238: iload           104
        //  1240: ixor           
        //  1241: istore          104
        //  1243: goto            809
        //  1246: ldc             481853128
        //  1248: iload           104
        //  1250: ixor           
        //  1251: istore          104
        //  1253: goto            809
        //  1256: ldc             331636179
        //  1258: iload           104
        //  1260: ixor           
        //  1261: istore          104
        //  1263: goto            809
        //  1266: iload           104
        //  1268: ldc             2022142355
        //  1270: invokestatic    me/pi3ro/cuy/network/ByteClassLoader.ojfurpnnjakpinoa:(II)I
        //  1273: istore          104
        //  1275: goto            809
        //  1278: ldc             1678787157
        //  1280: iload           104
        //  1282: ixor           
        //  1283: istore          104
        //  1285: goto            809
        //  1288: ldc             111248331
        //  1290: iload           104
        //  1292: ixor           
        //  1293: istore          104
        //  1295: goto            809
        //  1298: iload           104
        //  1300: ldc             1588170117
        //  1302: invokestatic    me/pi3ro/cuy/network/ByteClassLoader.ojfurpnnjakpinoa:(II)I
        //  1305: istore          104
        //  1307: goto            809
        //  1310: iload           104
        //  1312: ldc             112998536
        //  1314: invokestatic    me/pi3ro/cuy/network/ByteClassLoader.ojfurpnnjakpinoa:(II)I
        //  1317: istore          104
        //  1319: goto            809
        //  1322: ldc             1251460836
        //  1324: iload           104
        //  1326: ixor           
        //  1327: istore          104
        //  1329: goto            809
        //  1332: iload           104
        //  1334: ldc             914478683
        //  1336: invokestatic    me/pi3ro/cuy/network/ByteClassLoader.ojfurpnnjakpinoa:(II)I
        //  1339: istore          104
        //  1341: goto            809
        //  1344: ldc             707960168
        //  1346: iload           104
        //  1348: ixor           
        //  1349: istore          104
        //  1351: goto            809
        //  1354: ldc             1681712666
        //  1356: iload           104
        //  1358: ixor           
        //  1359: istore          104
        //  1361: goto            809
        //  1364: ldc             1652612754
        //  1366: iload           104
        //  1368: ixor           
        //  1369: istore          104
        //  1371: goto            650
        //  1374: ldc             851928440
        //  1376: iload           104
        //  1378: ixor           
        //  1379: istore          104
        //  1381: goto            761
        //  1384: iload           104
        //  1386: invokestatic    dbjrsyajbkgezbtp/ogwwobatgayyjyld.gicktsuzorogcxcs:(I)I
        //  1389: lookupswitch {
        //          -1850429573: 1528
        //          -1593259998: 1550
        //          -1472674054: 1604
        //          -1158569590: 1560
        //          -1017756600: 1582
        //          51787322: 1614
        //          66841634: 1506
        //          316029792: 1496
        //          379075273: 1570
        //          402462897: 1518
        //          859735194: 1538
        //          1737409315: 1592
        //          default: 3275
        //        }
        //  1496: ldc             1008661491
        //  1498: iload           104
        //  1500: ixor           
        //  1501: istore          104
        //  1503: goto            698
        //  1506: iload           104
        //  1508: ldc             2117814555
        //  1510: invokestatic    me/pi3ro/cuy/network/ByteClassLoader.ojfurpnnjakpinoa:(II)I
        //  1513: istore          104
        //  1515: goto            698
        //  1518: ldc             482056073
        //  1520: iload           104
        //  1522: ixor           
        //  1523: istore          104
        //  1525: goto            698
        //  1528: ldc             1282580848
        //  1530: iload           104
        //  1532: ixor           
        //  1533: istore          104
        //  1535: goto            698
        //  1538: iload           104
        //  1540: ldc             2015618060
        //  1542: invokestatic    me/pi3ro/cuy/network/ByteClassLoader.ojfurpnnjakpinoa:(II)I
        //  1545: istore          104
        //  1547: goto            698
        //  1550: ldc             1785015707
        //  1552: iload           104
        //  1554: ixor           
        //  1555: istore          104
        //  1557: goto            698
        //  1560: ldc             1763311790
        //  1562: iload           104
        //  1564: ixor           
        //  1565: istore          104
        //  1567: goto            698
        //  1570: iload           104
        //  1572: ldc             479671238
        //  1574: invokestatic    me/pi3ro/cuy/network/ByteClassLoader.ojfurpnnjakpinoa:(II)I
        //  1577: istore          104
        //  1579: goto            698
        //  1582: ldc             640613398
        //  1584: iload           104
        //  1586: ixor           
        //  1587: istore          104
        //  1589: goto            698
        //  1592: iload           104
        //  1594: ldc             1387654395
        //  1596: invokestatic    me/pi3ro/cuy/network/ByteClassLoader.ojfurpnnjakpinoa:(II)I
        //  1599: istore          104
        //  1601: goto            698
        //  1604: ldc             1799564352
        //  1606: iload           104
        //  1608: ixor           
        //  1609: istore          104
        //  1611: goto            698
        //  1614: ldc             2116481624
        //  1616: iload           104
        //  1618: ixor           
        //  1619: istore          104
        //  1621: goto            698
        //  1624: iload           104
        //  1626: invokestatic    dbjrsyajbkgezbtp/ogwwobatgayyjyld.gicktsuzorogcxcs:(I)I
        //  1629: lookupswitch {
        //          -1137781653: 1668
        //          -232676103: 1656
        //          default: 3286
        //        }
        //  1656: iload           104
        //  1658: ldc             595408096
        //  1660: invokestatic    me/pi3ro/cuy/network/ByteClassLoader.ojfurpnnjakpinoa:(II)I
        //  1663: istore          104
        //  1665: goto            726
        //  1668: iload           104
        //  1670: ldc             1790761714
        //  1672: invokestatic    me/pi3ro/cuy/network/ByteClassLoader.ojfurpnnjakpinoa:(II)I
        //  1675: istore          104
        //  1677: goto            726
        //  1680: iload           104
        //  1682: invokestatic    dbjrsyajbkgezbtp/ogwwobatgayyjyld.gicktsuzorogcxcs:(I)I
        //  1685: tableswitch {
        //          2098149696: 1704
        //          default: 3297
        //        }
        //  1704: iload           104
        //  1706: iconst_0       
        //  1707: invokestatic    me/pi3ro/cuy/network/ByteClassLoader.ojfurpnnjakpinoa:(II)I
        //  1710: istore          104
        //  1712: goto            837
        //  1715: iload           104
        //  1717: invokestatic    dbjrsyajbkgezbtp/ogwwobatgayyjyld.gicktsuzorogcxcs:(I)I
        //  1720: lookupswitch {
        //          -1667836590: 1748
        //          907683938: 1758
        //          default: 3308
        //        }
        //  1748: ldc             1145186622
        //  1750: iload           104
        //  1752: ixor           
        //  1753: istore          104
        //  1755: goto            837
        //  1758: ldc             1360246424
        //  1760: iload           104
        //  1762: ixor           
        //  1763: istore          104
        //  1765: goto            837
        //  1768: iload           104
        //  1770: invokestatic    dbjrsyajbkgezbtp/ogwwobatgayyjyld.gicktsuzorogcxcs:(I)I
        //  1773: lookupswitch {
        //          -1850429573: 1902
        //          -1593259998: 1880
        //          -1472674054: 1936
        //          -1158569590: 1956
        //          -1017756600: 1946
        //          51787322: 1926
        //          66841634: 1892
        //          316029792: 1997
        //          379075273: 1986
        //          402462897: 1976
        //          859735194: 1914
        //          1737409315: 1966
        //          default: 3319
        //        }
        //  1880: iload           104
        //  1882: ldc             1226316155
        //  1884: invokestatic    me/pi3ro/cuy/network/ByteClassLoader.ojfurpnnjakpinoa:(II)I
        //  1887: istore          104
        //  1889: goto            726
        //  1892: ldc             1564900859
        //  1894: iload           104
        //  1896: ixor           
        //  1897: istore          104
        //  1899: goto            726
        //  1902: iload           104
        //  1904: ldc             1863292304
        //  1906: invokestatic    me/pi3ro/cuy/network/ByteClassLoader.ojfurpnnjakpinoa:(II)I
        //  1909: istore          104
        //  1911: goto            726
        //  1914: iload           104
        //  1916: ldc             1532940524
        //  1918: invokestatic    me/pi3ro/cuy/network/ByteClassLoader.ojfurpnnjakpinoa:(II)I
        //  1921: istore          104
        //  1923: goto            726
        //  1926: ldc             1566295736
        //  1928: iload           104
        //  1930: ixor           
        //  1931: istore          104
        //  1933: goto            726
        //  1936: ldc             1212029088
        //  1938: iload           104
        //  1940: ixor           
        //  1941: istore          104
        //  1943: goto            726
        //  1946: ldc             89377014
        //  1948: iload           104
        //  1950: ixor           
        //  1951: istore          104
        //  1953: goto            726
        //  1956: ldc             1248277582
        //  1958: iload           104
        //  1960: ixor           
        //  1961: istore          104
        //  1963: goto            726
        //  1966: ldc             1908987931
        //  1968: iload           104
        //  1970: ixor           
        //  1971: istore          104
        //  1973: goto            726
        //  1976: ldc             1069982569
        //  1978: iload           104
        //  1980: ixor           
        //  1981: istore          104
        //  1983: goto            726
        //  1986: ldc_w           1072301862
        //  1989: iload           104
        //  1991: ixor           
        //  1992: istore          104
        //  1994: goto            726
        //  1997: ldc_w           526632723
        //  2000: iload           104
        //  2002: ixor           
        //  2003: istore          104
        //  2005: goto            726
        //  2008: iload           104
        //  2010: invokestatic    dbjrsyajbkgezbtp/ogwwobatgayyjyld.yphcfoidvruxcacx:(I)I
        //  2013: lookupswitch {
        //          50361430: 2056
        //          142399327: 2008
        //          1199236028: 385
        //          1919540913: 3330
        //          default: 3330
        //        }
        //  2056: ldc_w           1994308114
        //  2059: iload           104
        //  2061: ixor           
        //  2062: istore          104
        //  2064: goto            385
        //  2067: iload           104
        //  2069: ldc_w           1450958440
        //  2072: invokestatic    me/pi3ro/cuy/network/ByteClassLoader.ojfurpnnjakpinoa:(II)I
        //  2075: istore          104
        //  2077: goto            632
        //  2080: iload           104
        //  2082: invokestatic    dbjrsyajbkgezbtp/ogwwobatgayyjyld.gicktsuzorogcxcs:(I)I
        //  2085: lookupswitch {
        //          -2112578885: 2438
        //          -1850429573: 2359
        //          -1593259998: 2348
        //          -1472674054: 2370
        //          -1165646477: 2392
        //          -1158569590: 2326
        //          -1137781653: 2280
        //          -1017756600: 2471
        //          -740696542: 2528
        //          -550248550: 2495
        //          -372767752: 2506
        //          -232676103: 2517
        //          51787322: 2414
        //          66841634: 2304
        //          316029792: 2337
        //          379075273: 2315
        //          402462897: 2293
        //          681843056: 2460
        //          750685874: 2425
        //          859735194: 2449
        //          1022262872: 2403
        //          1654923072: 2484
        //          1737409315: 2381
        //          default: 3338
        //        }
        //  2280: iload           104
        //  2282: ldc_w           1616193817
        //  2285: invokestatic    me/pi3ro/cuy/network/ByteClassLoader.ojfurpnnjakpinoa:(II)I
        //  2288: istore          104
        //  2290: goto            837
        //  2293: ldc_w           892293250
        //  2296: iload           104
        //  2298: ixor           
        //  2299: istore          104
        //  2301: goto            837
        //  2304: ldc_w           1471122960
        //  2307: iload           104
        //  2309: ixor           
        //  2310: istore          104
        //  2312: goto            837
        //  2315: ldc_w           889451725
        //  2318: iload           104
        //  2320: ixor           
        //  2321: istore          104
        //  2323: goto            837
        //  2326: ldc_w           1083099045
        //  2329: iload           104
        //  2331: ixor           
        //  2332: istore          104
        //  2334: goto            837
        //  2337: ldc_w           361379064
        //  2340: iload           104
        //  2342: ixor           
        //  2343: istore          104
        //  2345: goto            837
        //  2348: ldc_w           1139927696
        //  2351: iload           104
        //  2353: ixor           
        //  2354: istore          104
        //  2356: goto            837
        //  2359: ldc_w           1709598331
        //  2362: iload           104
        //  2364: ixor           
        //  2365: istore          104
        //  2367: goto            837
        //  2370: ldc_w           1121446731
        //  2373: iload           104
        //  2375: ixor           
        //  2376: istore          104
        //  2378: goto            837
        //  2381: ldc_w           2065771504
        //  2384: iload           104
        //  2386: ixor           
        //  2387: istore          104
        //  2389: goto            837
        //  2392: ldc_w           1619019578
        //  2395: iload           104
        //  2397: ixor           
        //  2398: istore          104
        //  2400: goto            837
        //  2403: ldc_w           273497183
        //  2406: iload           104
        //  2408: ixor           
        //  2409: istore          104
        //  2411: goto            837
        //  2414: ldc_w           1471296851
        //  2417: iload           104
        //  2419: ixor           
        //  2420: istore          104
        //  2422: goto            837
        //  2425: iload           104
        //  2427: ldc_w           1380393538
        //  2430: invokestatic    me/pi3ro/cuy/network/ByteClassLoader.ojfurpnnjakpinoa:(II)I
        //  2433: istore          104
        //  2435: goto            837
        //  2438: ldc_w           1737646275
        //  2441: iload           104
        //  2443: ixor           
        //  2444: istore          104
        //  2446: goto            837
        //  2449: ldc_w           1370956551
        //  2452: iload           104
        //  2454: ixor           
        //  2455: istore          104
        //  2457: goto            837
        //  2460: ldc_w           314863802
        //  2463: iload           104
        //  2465: ixor           
        //  2466: istore          104
        //  2468: goto            837
        //  2471: iload           104
        //  2473: ldc_w           263863069
        //  2476: invokestatic    me/pi3ro/cuy/network/ByteClassLoader.ojfurpnnjakpinoa:(II)I
        //  2479: istore          104
        //  2481: goto            837
        //  2484: ldc_w           461664380
        //  2487: iload           104
        //  2489: ixor           
        //  2490: istore          104
        //  2492: goto            837
        //  2495: ldc_w           1278642279
        //  2498: iload           104
        //  2500: ixor           
        //  2501: istore          104
        //  2503: goto            837
        //  2506: ldc_w           183104491
        //  2509: iload           104
        //  2511: ixor           
        //  2512: istore          104
        //  2514: goto            837
        //  2517: ldc_w           697616139
        //  2520: iload           104
        //  2522: ixor           
        //  2523: istore          104
        //  2525: goto            837
        //  2528: ldc_w           1303103568
        //  2531: iload           104
        //  2533: ixor           
        //  2534: istore          104
        //  2536: goto            837
        //  2539: new             Ljava/lang/RuntimeException;
        //  2542: dup            
        //  2543: ldc_w           "Error in hash"
        //  2546: invokespecial   java/lang/RuntimeException.<init>:(Ljava/lang/String;)V
        //  2549: athrow         
        //  2550: iload           104
        //  2552: invokestatic    dbjrsyajbkgezbtp/ogwwobatgayyjyld.gicktsuzorogcxcs:(I)I
        //  2555: lookupswitch {
        //          -2112578885: 3040
        //          -1850429573: 2979
        //          -1667836590: 3051
        //          -1593259998: 2968
        //          -1472674054: 2852
        //          -1165646477: 2922
        //          -1158569590: 3097
        //          -1137781653: 3108
        //          -1098408800: 2944
        //          -1017756600: 2885
        //          -740696542: 3086
        //          -550248550: 3016
        //          -372767752: 2815
        //          -317645648: 3143
        //          -232676103: 3119
        //          51787322: 2839
        //          66841634: 3156
        //          316029792: 3003
        //          379075273: 2826
        //          402462897: 3075
        //          681843056: 2804
        //          750685874: 2992
        //          859735194: 2933
        //          907683938: 2874
        //          1022262872: 3029
        //          1184565546: 3130
        //          1552113881: 2898
        //          1654923072: 3064
        //          1737409315: 2955
        //          1983254626: 2911
        //          default: 2863
        //        }
        //  2804: ldc_w           1476039953
        //  2807: iload           104
        //  2809: ixor           
        //  2810: istore          104
        //  2812: goto            3235
        //  2815: ldc_w           1339496000
        //  2818: iload           104
        //  2820: ixor           
        //  2821: istore          104
        //  2823: goto            3235
        //  2826: iload           104
        //  2828: ldc_w           1883050342
        //  2831: invokestatic    me/pi3ro/cuy/network/ByteClassLoader.ojfurpnnjakpinoa:(II)I
        //  2834: istore          104
        //  2836: goto            3235
        //  2839: iload           104
        //  2841: ldc_w           311218424
        //  2844: invokestatic    me/pi3ro/cuy/network/ByteClassLoader.ojfurpnnjakpinoa:(II)I
        //  2847: istore          104
        //  2849: goto            3235
        //  2852: ldc_w           132714208
        //  2855: iload           104
        //  2857: ixor           
        //  2858: istore          104
        //  2860: goto            3235
        //  2863: new             Ljava/lang/IllegalAccessException;
        //  2866: dup            
        //  2867: ldc_w           "Error in hash"
        //  2870: invokespecial   java/lang/IllegalAccessException.<init>:(Ljava/lang/String;)V
        //  2873: athrow         
        //  2874: ldc_w           338514739
        //  2877: iload           104
        //  2879: ixor           
        //  2880: istore          104
        //  2882: goto            3235
        //  2885: iload           104
        //  2887: ldc_w           1250221750
        //  2890: invokestatic    me/pi3ro/cuy/network/ByteClassLoader.ojfurpnnjakpinoa:(II)I
        //  2893: istore          104
        //  2895: goto            3235
        //  2898: iload           104
        //  2900: ldc_w           2038331940
        //  2903: invokestatic    me/pi3ro/cuy/network/ByteClassLoader.ojfurpnnjakpinoa:(II)I
        //  2906: istore          104
        //  2908: goto            3235
        //  2911: ldc_w           472437811
        //  2914: iload           104
        //  2916: ixor           
        //  2917: istore          104
        //  2919: goto            3235
        //  2922: ldc_w           633250449
        //  2925: iload           104
        //  2927: ixor           
        //  2928: istore          104
        //  2930: goto            3235
        //  2933: ldc_w           344573612
        //  2936: iload           104
        //  2938: ixor           
        //  2939: istore          104
        //  2941: goto            3235
        //  2944: ldc_w           1161749931
        //  2947: iload           104
        //  2949: ixor           
        //  2950: istore          104
        //  2952: goto            3235
        //  2955: iload           104
        //  2957: ldc_w           1042271835
        //  2960: invokestatic    me/pi3ro/cuy/network/ByteClassLoader.ojfurpnnjakpinoa:(II)I
        //  2963: istore          104
        //  2965: goto            3235
        //  2968: ldc_w           114233147
        //  2971: iload           104
        //  2973: ixor           
        //  2974: istore          104
        //  2976: goto            3235
        //  2979: iload           104
        //  2981: ldc_w           551060432
        //  2984: invokestatic    me/pi3ro/cuy/network/ByteClassLoader.ojfurpnnjakpinoa:(II)I
        //  2987: istore          104
        //  2989: goto            3235
        //  2992: ldc_w           393857001
        //  2995: iload           104
        //  2997: ixor           
        //  2998: istore          104
        //  3000: goto            3235
        //  3003: iload           104
        //  3005: ldc_w           1354027347
        //  3008: invokestatic    me/pi3ro/cuy/network/ByteClassLoader.ojfurpnnjakpinoa:(II)I
        //  3011: istore          104
        //  3013: goto            3235
        //  3016: iload           104
        //  3018: ldc_w           151547340
        //  3021: invokestatic    me/pi3ro/cuy/network/ByteClassLoader.ojfurpnnjakpinoa:(II)I
        //  3024: istore          104
        //  3026: goto            3235
        //  3029: ldc_w           1433655796
        //  3032: iload           104
        //  3034: ixor           
        //  3035: istore          104
        //  3037: goto            3235
        //  3040: ldc_w           581731688
        //  3043: iload           104
        //  3045: ixor           
        //  3046: istore          104
        //  3048: goto            3235
        //  3051: iload           104
        //  3053: ldc_w           24956053
        //  3056: invokestatic    me/pi3ro/cuy/network/ByteClassLoader.ojfurpnnjakpinoa:(II)I
        //  3059: istore          104
        //  3061: goto            3235
        //  3064: ldc_w           1589286359
        //  3067: iload           104
        //  3069: ixor           
        //  3070: istore          104
        //  3072: goto            3235
        //  3075: ldc_w           1880208681
        //  3078: iload           104
        //  3080: ixor           
        //  3081: istore          104
        //  3083: goto            3235
        //  3086: ldc_w           143994363
        //  3089: iload           104
        //  3091: ixor           
        //  3092: istore          104
        //  3094: goto            3235
        //  3097: ldc_w           95429134
        //  3100: iload           104
        //  3102: ixor           
        //  3103: istore          104
        //  3105: goto            3235
        //  3108: ldc_w           627821746
        //  3111: iload           104
        //  3113: ixor           
        //  3114: istore          104
        //  3116: goto            3235
        //  3119: ldc_w           1823089312
        //  3122: iload           104
        //  3124: ixor           
        //  3125: istore          104
        //  3127: goto            3235
        //  3130: iload           104
        //  3132: ldc_w           440235802
        //  3135: invokestatic    me/pi3ro/cuy/network/ByteClassLoader.ojfurpnnjakpinoa:(II)I
        //  3138: istore          104
        //  3140: goto            3235
        //  3143: iload           104
        //  3145: ldc_w           1330394537
        //  3148: invokestatic    me/pi3ro/cuy/network/ByteClassLoader.ojfurpnnjakpinoa:(II)I
        //  3151: istore          104
        //  3153: goto            3235
        //  3156: ldc_w           311520187
        //  3159: iload           104
        //  3161: ixor           
        //  3162: istore          104
        //  3164: goto            3235
        //  3167: new             Ljava/lang/RuntimeException;
        //  3170: dup            
        //  3171: ldc_w           "Error in hash"
        //  3174: invokespecial   java/lang/RuntimeException.<init>:(Ljava/lang/String;)V
        //  3177: athrow         
        //  3178: iload           104
        //  3180: invokestatic    dbjrsyajbkgezbtp/ogwwobatgayyjyld.yphcfoidvruxcacx:(I)I
        //  3183: lookupswitch {
        //          157956432: 3224
        //          370167204: 3330
        //          1319387472: 3266
        //          1356852084: 3178
        //          default: 3330
        //        }
        //  3224: ldc_w           101221207
        //  3227: iload           104
        //  3229: ixor           
        //  3230: istore          104
        //  3232: goto            3266
        //  3235: astore          42
        //  3237: aload           42
        //  3239: astore          96
        //  3241: ldc_w           333256853
        //  3244: iload           104
        //  3246: ixor           
        //  3247: istore          104
        //  3249: aload           96
        //  3251: astore          43
        //  3253: aload           43
        //  3255: invokevirtual   java/lang/Exception.printStackTrace:()V
        //  3258: ldc_w           1520021099
        //  3261: iload           104
        //  3263: ixor           
        //  3264: istore          104
        //  3266: ldc_w           248107486
        //  3269: iload           104
        //  3271: ixor           
        //  3272: istore          104
        //  3274: return         
        //  3275: new             Ljava/lang/IllegalAccessException;
        //  3278: dup            
        //  3279: ldc_w           "Error in hash"
        //  3282: invokespecial   java/lang/IllegalAccessException.<init>:(Ljava/lang/String;)V
        //  3285: athrow         
        //  3286: new             Ljava/io/IOException;
        //  3289: dup            
        //  3290: ldc_w           "Error in hash"
        //  3293: invokespecial   java/io/IOException.<init>:(Ljava/lang/String;)V
        //  3296: athrow         
        //  3297: new             Ljava/io/IOException;
        //  3300: dup            
        //  3301: ldc_w           "Error in hash"
        //  3304: invokespecial   java/io/IOException.<init>:(Ljava/lang/String;)V
        //  3307: athrow         
        //  3308: new             Ljava/io/IOException;
        //  3311: dup            
        //  3312: ldc_w           "Error in hash"
        //  3315: invokespecial   java/io/IOException.<init>:(Ljava/lang/String;)V
        //  3318: athrow         
        //  3319: new             Ljava/io/IOException;
        //  3322: dup            
        //  3323: ldc_w           "Error in hash"
        //  3326: invokespecial   java/io/IOException.<init>:(Ljava/lang/String;)V
        //  3329: athrow         
        //  3330: new             Ljava/io/IOException;
        //  3333: dup            
        //  3334: invokespecial   java/io/IOException.<init>:()V
        //  3337: athrow         
        //  3338: new             Ljava/lang/IllegalAccessException;
        //  3341: dup            
        //  3342: ldc_w           "Error in hash"
        //  3345: invokespecial   java/lang/IllegalAccessException.<init>:(Ljava/lang/String;)V
        //  3348: athrow         
        //    StackMapTable: 00 92 FF 00 43 00 69 07 00 02 07 01 4F 07 01 51 01 07 01 4F 07 01 53 07 01 51 00 00 00 00 00 00 00 00 00 00 00 00 00 07 01 51 07 00 02 00 00 00 00 00 00 00 00 00 00 00 00 00 00 00 00 00 00 00 00 00 00 00 00 00 00 00 00 00 00 00 00 00 00 00 00 00 00 00 00 00 00 00 00 00 00 00 00 00 07 01 53 01 07 01 55 00 00 00 00 00 00 00 00 00 00 00 00 00 00 00 00 00 00 00 00 00 00 00 00 00 00 00 00 00 00 01 00 00 30 06 FF 01 05 00 69 07 00 02 07 01 4F 07 01 51 01 07 01 4F 07 01 53 07 01 51 00 00 00 07 00 6A 05 07 00 65 01 07 00 6A 05 07 00 6F 01 07 00 7F 00 07 01 51 07 00 02 07 00 02 07 00 65 07 00 6A 05 07 00 6A 07 00 65 01 07 00 6F 07 00 6A 05 07 00 6A 07 00 6F 01 07 00 6F 07 00 7F 00 00 00 00 00 00 00 00 00 00 00 00 00 00 00 00 00 00 00 00 00 00 00 00 00 00 00 00 00 00 00 00 00 00 07 01 53 01 07 01 55 07 00 5B 00 00 00 00 00 00 00 00 00 07 01 4F 07 00 65 07 00 71 00 00 00 00 00 00 00 00 00 00 00 00 00 00 00 00 00 01 00 00 FF 00 F6 00 69 07 00 02 07 01 4F 07 01 51 01 07 01 4F 07 01 53 07 01 51 00 00 00 07 00 6A 05 07 00 65 01 07 00 6A 05 07 00 6F 01 07 00 7F 00 07 01 51 07 00 02 07 00 02 07 00 65 07 00 6A 05 07 00 6A 07 00 65 01 07 00 6F 07 00 6A 05 07 00 6A 07 00 6F 01 07 00 6F 07 00 7F 07 00 7F 00 00 00 00 00 00 00 00 00 00 00 00 00 00 00 00 00 00 07 00 7F 01 00 00 00 00 00 00 00 00 00 00 00 00 00 07 01 53 01 07 01 55 07 00 5B 00 00 00 00 00 00 00 00 00 07 01 4F 07 00 65 07 00 71 00 00 00 00 00 00 00 00 00 00 00 00 00 00 00 00 00 01 00 00 FF 00 11 00 69 07 00 02 07 01 4F 07 01 51 01 07 01 4F 07 01 53 07 01 51 00 00 00 07 00 6A 05 07 00 65 01 07 00 6A 05 07 00 6F 01 07 00 7F 00 07 01 51 07 00 02 07 00 02 07 00 65 07 00 6A 05 07 00 6A 07 00 65 01 07 00 6F 07 00 6A 05 07 00 6A 07 00 6F 01 07 00 6F 07 00 7F 07 00 7F 00 00 00 00 00 00 00 00 00 00 00 00 00 00 00 00 00 00 00 00 00 00 00 00 00 00 00 00 00 00 00 00 00 07 01 53 01 07 01 55 07 00 5B 00 00 00 00 00 00 00 00 00 07 01 4F 07 00 65 07 00 71 00 00 00 00 00 00 00 00 00 00 00 00 00 00 00 00 00 01 00 00 FF 00 2F 00 69 07 00 02 07 01 4F 07 01 51 01 07 01 4F 07 01 53 07 01 51 00 00 00 07 00 6A 05 07 00 65 01 07 00 6A 05 00 00 00 00 07 01 51 07 00 02 07 00 02 07 00 65 07 00 6A 05 07 00 6A 07 00 65 01 07 00 6F 07 00 6A 05 00 00 00 00 00 00 00 00 00 00 00 00 00 00 00 00 00 00 00 00 00 00 00 00 00 00 00 00 00 00 00 00 00 00 00 00 00 00 00 07 01 53 01 07 01 55 07 00 5B 00 00 00 00 00 00 00 00 00 07 01 4F 07 00 65 07 00 71 00 00 00 00 00 00 00 00 00 00 00 00 00 00 00 00 00 01 00 01 07 00 2B FF 00 1B 00 69 07 00 02 07 01 4F 07 01 51 01 07 01 4F 07 01 53 07 01 51 00 00 00 07 00 6A 05 07 00 65 01 07 00 6A 07 00 2B 00 00 00 00 07 01 51 07 00 02 07 00 02 07 00 65 07 00 6A 05 07 00 6A 07 00 65 01 07 00 6F 07 00 6A 05 00 00 00 00 00 00 00 00 00 00 00 00 00 00 00 00 00 00 00 00 00 00 00 00 00 00 00 00 00 00 00 00 00 00 00 00 00 00 00 07 01 53 01 07 01 55 07 00 5B 00 00 00 00 00 00 00 00 00 07 01 4F 07 00 65 07 00 71 00 00 00 00 00 00 00 00 00 00 00 00 00 00 00 00 00 01 00 01 07 00 2B FF 00 22 00 69 07 00 02 07 01 4F 07 01 51 01 07 01 4F 07 01 53 07 01 51 00 00 00 07 00 6A 05 07 00 65 01 07 00 6A 05 07 00 6F 01 07 00 7F 00 07 01 51 07 00 02 07 00 02 07 00 65 07 00 6A 05 07 00 6A 07 00 65 01 07 00 6F 07 00 6A 05 07 00 6A 07 00 6F 01 07 00 6F 07 00 7F 07 00 7F 07 00 B5 07 00 6A 00 00 00 00 00 00 00 00 00 00 00 00 00 00 00 00 00 00 00 00 00 00 00 00 00 00 00 00 00 00 00 07 01 53 01 07 01 55 07 00 5B 05 00 00 00 00 00 00 00 00 07 01 4F 07 00 65 07 00 71 00 00 00 00 00 00 00 00 00 00 00 00 00 07 00 B5 00 00 00 01 00 00 FF 00 2F 00 69 07 00 02 07 01 4F 07 01 51 01 07 01 4F 07 01 53 07 01 51 00 00 00 07 00 6A 05 00 00 00 00 00 00 00 00 07 01 51 07 00 02 07 00 02 07 00 65 07 00 6A 05 00 00 00 00 00 00 00 00 00 00 00 00 00 00 00 00 00 00 00 00 00 00 00 00 00 00 00 00 00 00 00 00 00 00 00 00 00 00 00 00 00 00 00 00 00 07 01 53 01 07 01 55 07 00 5B 00 00 00 00 00 00 00 00 00 07 01 4F 00 00 00 00 00 00 00 00 00 00 00 00 00 00 00 00 00 00 00 01 00 01 07 00 2B FF 00 1B 00 69 07 00 02 07 01 4F 07 01 51 01 07 01 4F 07 01 53 07 01 51 00 00 00 07 00 6A 07 00 2B 00 00 00 00 00 00 00 00 07 01 51 07 00 02 07 00 02 07 00 65 07 00 6A 05 00 00 00 00 00 00 00 00 00 00 00 00 00 00 00 00 00 00 00 00 00 00 00 00 00 00 00 00 00 00 00 00 00 00 00 00 00 00 00 00 00 00 00 00 00 07 01 53 01 07 01 55 07 00 5B 00 00 00 00 00 00 00 00 00 07 01 4F 00 00 00 00 00 00 00 00 00 00 00 00 00 00 00 00 00 00 00 01 00 01 07 00 2B FF 00 22 00 69 07 00 02 07 01 4F 07 01 51 01 07 01 4F 07 01 53 07 01 51 00 00 00 07 00 6A 05 07 00 65 01 07 00 6A 07 00 2B 00 00 00 00 07 01 51 07 00 02 07 00 02 07 00 65 07 00 6A 05 07 00 6A 07 00 65 01 07 00 6F 07 00 6A 05 00 00 00 00 00 00 00 00 00 00 00 00 00 00 00 00 00 00 00 00 00 00 00 00 00 00 00 00 00 00 00 00 00 00 00 00 00 00 00 07 01 53 01 07 01 55 07 00 5B 00 00 00 00 00 00 00 00 00 07 01 4F 07 00 65 07 00 71 00 00 00 00 00 00 00 00 00 00 00 00 00 00 00 00 00 01 00 01 07 00 2B 57 07 00 2B FF 00 0A 00 69 07 00 02 07 01 4F 07 01 51 01 07 01 4F 07 01 53 07 01 51 00 00 00 07 00 6A 05 07 00 65 01 07 00 6A 05 07 00 6F 01 07 00 7F 00 07 01 51 07 00 02 07 00 02 07 00 65 07 00 6A 05 07 00 6A 07 00 65 01 07 00 6F 07 00 6A 05 07 00 6A 07 00 6F 01 07 00 6F 07 00 7F 07 00 7F 00 00 00 00 00 00 00 00 00 00 00 00 00 00 00 00 00 00 07 00 7F 01 00 00 00 00 00 00 00 00 00 00 00 00 00 07 01 53 01 07 01 55 07 00 5B 00 00 00 00 00 00 00 00 00 07 01 4F 07 00 65 07 00 71 00 00 00 00 00 00 00 00 00 00 00 00 00 00 00 00 00 01 00 00 FF 00 09 00 69 07 00 02 07 01 4F 07 01 51 01 07 01 4F 07 01 53 07 01 51 00 00 00 07 00 6A 05 00 00 00 00 00 00 00 00 07 01 51 07 00 02 07 00 02 07 00 65 07 00 6A 05 00 00 00 00 00 00 00 00 00 00 00 00 00 00 00 00 00 00 00 00 00 00 00 00 00 00 00 00 00 00 00 00 00 00 00 00 00 00 00 00 00 00 00 00 00 07 01 53 01 07 01 55 07 00 5B 00 00 00 00 00 00 00 00 00 07 01 4F 00 00 00 00 00 00 00 00 00 00 00 00 00 00 00 00 00 00 00 01 00 01 07 00 2B F7 00 C6 07 00 2B 4B 07 00 2B 4B 07 00 2B 4B 07 00 2B 49 07 00 2B 49 07 00 2B 4B 07 00 2B 49 07 00 2B 4B 07 00 2B 49 07 00 2B 49 07 00 2B 49 07 00 2B 49 07 00 2B 49 07 00 2B 49 07 00 2B 4B 07 00 2B 49 07 00 2B 49 07 00 2B 4B 07 00 2B 4B 07 00 2B 49 07 00 2B 4B 07 00 2B 49 07 00 2B FF 00 09 00 69 07 00 02 07 01 4F 07 01 51 01 07 01 4F 07 01 53 07 01 51 00 00 00 07 00 6A 05 07 00 65 01 07 00 6A 05 07 00 6F 01 07 00 7F 00 07 01 51 07 00 02 07 00 02 07 00 65 07 00 6A 05 07 00 6A 07 00 65 01 07 00 6F 07 00 6A 05 07 00 6A 07 00 6F 01 07 00 6F 07 00 7F 07 00 7F 00 00 00 00 00 00 00 00 00 00 00 00 00 00 00 00 00 00 00 00 00 00 00 00 00 00 00 00 00 00 00 00 00 07 01 53 01 07 01 55 07 00 5B 00 00 00 00 00 00 00 00 00 07 01 4F 07 00 65 07 00 71 00 00 00 00 00 00 00 00 00 00 00 00 00 00 00 00 00 01 00 00 FF 00 09 00 69 07 00 02 07 01 4F 07 01 51 01 07 01 4F 07 01 53 07 01 51 00 00 00 07 00 6A 05 07 00 65 01 07 00 6A 05 07 00 6F 01 07 00 7F 00 07 01 51 07 00 02 07 00 02 07 00 65 07 00 6A 05 07 00 6A 07 00 65 01 07 00 6F 07 00 6A 05 07 00 6A 07 00 6F 01 07 00 6F 07 00 7F 07 00 7F 07 00 B5 07 00 6A 00 00 00 00 00 00 00 00 00 00 00 00 00 00 00 00 00 00 00 00 00 00 00 00 00 00 00 00 00 00 00 07 01 53 01 07 01 55 07 00 5B 05 00 00 00 00 00 00 00 00 07 01 4F 07 00 65 07 00 71 00 00 00 00 00 00 00 00 00 00 00 00 00 07 00 B5 00 00 00 01 00 00 FF 00 09 00 69 07 00 02 07 01 4F 07 01 51 01 07 01 4F 07 01 53 07 01 51 00 00 00 07 00 6A 05 07 00 65 01 07 00 6A 05 00 00 00 00 07 01 51 07 00 02 07 00 02 07 00 65 07 00 6A 05 07 00 6A 07 00 65 01 07 00 6F 07 00 6A 05 00 00 00 00 00 00 00 00 00 00 00 00 00 00 00 00 00 00 00 00 00 00 00 00 00 00 00 00 00 00 00 00 00 00 00 00 00 00 00 07 01 53 01 07 01 55 07 00 5B 00 00 00 00 00 00 00 00 00 07 01 4F 07 00 65 07 00 71 00 00 00 00 00 00 00 00 00 00 00 00 00 00 00 00 00 01 00 01 07 00 2B F7 00 6F 07 00 2B 49 07 00 2B 4B 07 00 2B 49 07 00 2B 49 07 00 2B 4B 07 00 2B 49 07 00 2B 49 07 00 2B 4B 07 00 2B 49 07 00 2B 4B 07 00 2B 49 07 00 2B FF 00 09 00 69 07 00 02 07 01 4F 07 01 51 01 07 01 4F 07 01 53 07 01 51 00 00 00 07 00 6A 05 07 00 65 01 07 00 6A 07 00 2B 00 00 00 00 07 01 51 07 00 02 07 00 02 07 00 65 07 00 6A 05 07 00 6A 07 00 65 01 07 00 6F 07 00 6A 05 00 00 00 00 00 00 00 00 00 00 00 00 00 00 00 00 00 00 00 00 00 00 00 00 00 00 00 00 00 00 00 00 00 00 00 00 00 00 00 07 01 53 01 07 01 55 07 00 5B 00 00 00 00 00 00 00 00 00 07 01 4F 07 00 65 07 00 71 00 00 00 00 00 00 00 00 00 00 00 00 00 00 00 00 00 01 00 01 07 00 2B 5F 07 00 2B 4B 07 00 2B FF 00 0B 00 69 07 00 02 07 01 4F 07 01 51 01 07 01 4F 07 01 53 07 01 51 00 00 00 07 00 6A 07 00 2B 00 00 00 00 00 00 00 00 07 01 51 07 00 02 07 00 02 07 00 65 07 00 6A 05 00 00 00 00 00 00 00 00 00 00 00 00 00 00 00 00 00 00 00 00 00 00 00 00 00 00 00 00 00 00 00 00 00 00 00 00 00 00 00 00 00 00 00 00 00 07 01 53 01 07 01 55 07 00 5B 00 00 00 00 00 00 00 00 00 07 01 4F 00 00 00 00 00 00 00 00 00 00 00 00 00 00 00 00 00 00 00 01 00 01 07 00 2B 57 07 00 2B 4A 07 00 2B 60 07 00 2B 49 07 00 2B FF 00 09 00 69 07 00 02 07 01 4F 07 01 51 01 07 01 4F 07 01 53 07 01 51 00 00 00 07 00 6A 05 07 00 65 01 07 00 6A 05 00 00 00 00 07 01 51 07 00 02 07 00 02 07 00 65 07 00 6A 05 07 00 6A 07 00 65 01 07 00 6F 07 00 6A 05 00 00 00 00 00 00 00 00 00 00 00 00 00 00 00 00 00 00 00 00 00 00 00 00 00 00 00 00 00 00 00 00 00 00 00 00 00 00 00 07 01 53 01 07 01 55 07 00 5B 00 00 00 00 00 00 00 00 00 07 01 4F 07 00 65 07 00 71 00 00 00 00 00 00 00 00 00 00 00 00 00 00 00 00 00 01 00 01 07 00 2B F7 00 6F 07 00 2B 4B 07 00 2B 49 07 00 2B 4B 07 00 2B 4B 07 00 2B 49 07 00 2B 49 07 00 2B 49 07 00 2B 49 07 00 2B 49 07 00 2B 49 07 00 2B 4A 07 00 2B FF 00 0A 00 69 07 00 02 07 01 4F 07 01 51 01 07 01 4F 07 01 53 07 01 51 00 00 00 07 00 6A 05 07 00 65 01 07 00 6A 05 07 00 6F 01 07 00 7F 00 07 01 51 07 00 02 07 00 02 07 00 65 07 00 6A 05 07 00 6A 07 00 65 01 07 00 6F 07 00 6A 05 07 00 6A 07 00 6F 01 07 00 6F 07 00 7F 07 00 7F 00 00 00 00 00 00 00 00 00 00 00 00 00 00 00 00 00 00 07 00 7F 01 00 00 00 00 00 00 00 00 00 00 00 07 00 6F 07 00 7F 07 01 53 01 07 01 55 07 00 5B 00 00 00 00 00 00 00 00 00 07 01 4F 07 00 65 07 00 71 00 00 00 00 00 00 00 00 00 00 00 00 00 00 00 00 00 01 00 00 2F FF 00 0A 00 69 07 00 02 07 01 4F 07 01 51 01 07 01 4F 07 01 53 07 01 51 01 05 00 07 00 6A 05 07 00 65 01 07 00 6A 05 07 00 6F 01 07 00 7F 00 07 01 51 07 00 02 07 00 02 07 00 65 07 00 6A 05 07 00 6A 07 00 65 01 07 00 6F 07 00 6A 05 07 00 6A 07 00 6F 01 07 00 6F 07 00 7F 07 00 7F 00 00 00 00 00 00 00 00 00 00 00 00 00 00 00 00 00 00 07 00 7F 01 07 00 7F 07 01 53 01 00 00 00 00 00 00 00 00 00 00 07 01 53 01 07 01 55 07 00 5B 00 00 00 00 07 01 53 00 00 00 00 07 01 4F 07 00 65 07 00 71 07 01 53 01 00 00 00 00 00 00 00 00 00 00 00 00 00 00 00 01 00 00 FF 00 0C 00 69 07 00 02 07 01 4F 07 01 51 01 07 01 4F 07 01 53 07 01 51 00 00 00 07 00 6A 05 00 00 00 00 00 00 00 00 07 01 51 07 00 02 07 00 02 07 00 65 07 00 6A 05 00 00 00 00 00 00 00 00 00 00 00 00 00 00 00 00 00 00 00 00 00 00 00 00 00 00 00 00 00 00 00 00 00 00 00 00 00 00 00 00 00 00 00 00 00 07 01 53 01 07 01 55 07 00 5B 00 00 00 00 00 00 00 00 00 07 01 4F 00 00 00 00 00 00 00 00 00 00 00 00 00 00 00 00 00 00 00 01 00 01 07 00 2B F7 00 C7 07 00 2B 4C 07 00 2B 4A 07 00 2B 4A 07 00 2B 4A 07 00 2B 4A 07 00 2B 4A 07 00 2B 4A 07 00 2B 4A 07 00 2B 4A 07 00 2B 4A 07 00 2B 4A 07 00 2B 4A 07 00 2B 4A 07 00 2B 4C 07 00 2B 4A 07 00 2B 4A 07 00 2B 4A 07 00 2B 4C 07 00 2B 4A 07 00 2B 4A 07 00 2B 4A 07 00 2B 4A 07 00 2B FF 00 0A 00 69 07 00 02 07 01 4F 07 01 51 01 07 01 4F 07 01 53 07 01 51 00 00 00 07 00 6A 05 07 00 65 01 07 00 6A 07 00 2B 00 00 00 00 07 01 51 07 00 02 07 00 02 07 00 65 07 00 6A 05 07 00 6A 07 00 65 01 07 00 6F 07 00 6A 05 00 00 00 00 00 00 00 00 00 00 00 00 00 00 00 00 00 00 00 00 00 00 00 00 00 00 00 00 00 00 00 00 00 00 00 00 00 00 00 07 01 53 01 07 01 55 07 00 5B 00 00 00 00 00 00 00 00 00 07 01 4F 07 00 65 07 00 71 00 00 00 00 00 00 00 00 00 00 00 00 00 00 00 00 00 01 00 01 07 00 2B FF 00 0A 00 69 07 00 02 07 01 4F 07 01 51 01 07 01 4F 07 01 53 07 01 51 00 00 00 00 00 00 00 00 00 00 00 00 00 07 01 51 07 00 02 07 00 02 00 00 00 00 00 00 00 00 00 00 00 00 00 00 00 00 00 00 00 00 00 00 00 00 00 00 00 00 00 00 00 00 00 00 00 00 00 00 00 00 00 00 00 00 00 00 00 00 07 01 53 01 07 01 55 07 00 5B 00 00 00 00 00 00 00 00 00 00 00 00 00 00 00 00 00 00 00 00 00 00 00 00 00 00 00 00 00 01 00 01 07 00 2D F7 00 FD 07 00 2D 4A 07 00 2D 4A 07 00 2D 4C 07 00 2D 4C 07 00 2D 4A 07 00 2D 4A 07 00 2D 4A 07 00 2D 4C 07 00 2D 4C 07 00 2D 4A 07 00 2D 4A 07 00 2D 4A 07 00 2D 4A 07 00 2D 4C 07 00 2D 4A 07 00 2D 4C 07 00 2D 4A 07 00 2D 4C 07 00 2D 4C 07 00 2D 4A 07 00 2D 4A 07 00 2D 4C 07 00 2D 4A 07 00 2D 4A 07 00 2D 4A 07 00 2D 4A 07 00 2D 4A 07 00 2D 4A 07 00 2D 4C 07 00 2D 4C 07 00 2D FF 00 0A 00 69 07 00 02 07 01 4F 07 01 51 01 07 01 4F 07 01 53 07 01 51 00 00 00 07 00 6A 05 00 00 00 00 00 00 00 00 07 01 51 07 00 02 07 00 02 07 00 65 07 00 6A 05 00 00 00 00 00 00 00 00 00 00 00 00 00 00 00 00 00 00 00 00 00 00 00 00 00 00 00 00 00 00 00 00 00 00 00 00 00 00 00 00 00 00 00 00 00 07 01 53 01 07 01 55 07 00 5B 00 00 00 00 00 00 00 00 00 07 01 4F 00 00 00 00 00 00 00 00 00 00 00 00 00 00 00 00 00 00 00 01 00 01 07 00 2B FF 00 0A 00 69 07 00 02 07 01 4F 07 01 51 01 07 01 4F 07 01 53 07 01 51 00 00 00 07 00 6A 05 07 00 65 01 07 00 6A 05 07 00 6F 01 07 00 7F 00 07 01 51 07 00 02 07 00 02 07 00 65 07 00 6A 05 07 00 6A 07 00 65 01 07 00 6F 07 00 6A 05 07 00 6A 07 00 6F 01 07 00 6F 07 00 7F 07 00 7F 07 00 B5 07 00 6A 07 00 B5 07 00 6A 00 00 00 00 00 00 00 00 00 00 00 00 00 00 00 00 00 00 00 00 00 00 00 00 00 00 00 00 00 07 01 53 01 07 01 55 07 00 5B 05 05 00 00 00 00 00 00 00 07 01 4F 07 00 65 07 00 71 00 00 00 00 00 00 00 00 00 00 07 00 B5 00 00 07 00 B5 00 00 00 01 00 00 2D FF 00 0A 00 69 07 00 02 07 01 4F 07 01 51 01 07 01 4F 07 01 53 07 01 51 00 00 00 00 00 00 00 00 00 00 00 00 00 07 01 51 07 00 02 07 00 02 00 00 00 00 00 00 00 00 00 00 00 00 00 00 00 00 00 00 00 00 00 00 00 00 00 00 00 00 00 00 00 00 00 00 00 00 00 00 00 00 00 00 00 00 00 00 00 00 07 01 53 01 07 01 55 07 00 5B 00 00 00 00 00 00 00 00 00 00 00 00 00 00 00 00 00 00 00 00 00 00 00 00 00 00 00 00 00 01 00 01 07 00 2D 1E FF 00 08 00 69 07 00 02 07 01 4F 07 01 51 01 07 01 4F 07 01 53 07 01 51 00 00 00 07 00 6A 05 07 00 65 01 07 00 6A 05 00 00 00 00 07 01 51 07 00 02 07 00 02 07 00 65 07 00 6A 05 07 00 6A 07 00 65 01 07 00 6F 07 00 6A 05 00 00 00 00 00 00 00 00 00 00 00 00 00 00 00 00 00 00 00 00 00 00 00 00 00 00 00 00 00 00 00 00 00 00 00 00 00 00 00 07 01 53 01 07 01 55 07 00 5B 00 00 00 00 00 00 00 00 00 07 01 4F 07 00 65 07 00 71 00 00 00 00 00 00 00 00 00 00 00 00 00 00 00 00 00 01 00 01 07 00 2B FF 00 0A 00 69 07 00 02 07 01 4F 07 01 51 01 07 01 4F 07 01 53 07 01 51 00 00 00 07 00 6A 05 07 00 65 01 07 00 6A 07 00 2B 00 00 00 00 07 01 51 07 00 02 07 00 02 07 00 65 07 00 6A 05 07 00 6A 07 00 65 01 07 00 6F 07 00 6A 05 00 00 00 00 00 00 00 00 00 00 00 00 00 00 00 00 00 00 00 00 00 00 00 00 00 00 00 00 00 00 00 00 00 00 00 00 00 00 00 07 01 53 01 07 01 55 07 00 5B 00 00 00 00 00 00 00 00 00 07 01 4F 07 00 65 07 00 71 00 00 00 00 00 00 00 00 00 00 00 00 00 00 00 00 00 01 00 01 07 00 2B FF 00 0A 00 69 07 00 02 07 01 4F 07 01 51 01 07 01 4F 07 01 53 07 01 51 00 00 00 07 00 6A 07 00 2B 00 00 00 00 00 00 00 00 07 01 51 07 00 02 07 00 02 07 00 65 07 00 6A 05 00 00 00 00 00 00 00 00 00 00 00 00 00 00 00 00 00 00 00 00 00 00 00 00 00 00 00 00 00 00 00 00 00 00 00 00 00 00 00 00 00 00 00 00 00 07 01 53 01 07 01 55 07 00 5B 00 00 00 00 00 00 00 00 00 07 01 4F 00 00 00 00 00 00 00 00 00 00 00 00 00 00 00 00 00 00 00 01 00 01 07 00 2B 4A 07 00 2B FF 00 0A 00 69 07 00 02 07 01 4F 07 01 51 01 07 01 4F 07 01 53 07 01 51 00 00 00 07 00 6A 05 07 00 65 01 07 00 6A 05 00 00 00 00 07 01 51 07 00 02 07 00 02 07 00 65 07 00 6A 05 07 00 6A 07 00 65 01 07 00 6F 07 00 6A 05 00 00 00 00 00 00 00 00 00 00 00 00 00 00 00 00 00 00 00 00 00 00 00 00 00 00 00 00 00 00 00 00 00 00 00 00 00 00 00 07 01 53 01 07 01 55 07 00 5B 00 00 00 00 00 00 00 00 00 07 01 4F 07 00 65 07 00 71 00 00 00 00 00 00 00 00 00 00 00 00 00 00 00 00 00 01 00 01 07 00 2B FF 00 0A 00 69 07 00 02 07 01 4F 07 01 51 01 07 01 4F 07 01 53 07 01 51 00 00 00 00 00 00 00 00 00 00 00 00 00 07 01 51 07 00 02 00 00 00 00 00 00 00 00 00 00 00 00 00 00 00 00 00 00 00 00 00 00 00 00 00 00 00 00 00 00 00 00 00 00 00 00 00 00 00 00 00 00 00 00 00 00 00 00 00 07 01 53 01 07 01 55 00 00 00 00 00 00 00 00 00 00 00 00 00 00 00 00 00 00 00 00 00 00 00 00 00 00 00 00 00 00 01 00 00 FF 00 07 00 69 07 00 02 07 01 4F 07 01 51 01 07 01 4F 07 01 53 07 01 51 00 00 00 07 00 6A 05 00 00 00 00 00 00 00 00 07 01 51 07 00 02 07 00 02 07 00 65 07 00 6A 05 00 00 00 00 00 00 00 00 00 00 00 00 00 00 00 00 00 00 00 00 00 00 00 00 00 00 00 00 00 00 00 00 00 00 00 00 00 00 00 00 00 00 00 00 00 07 01 53 01 07 01 55 07 00 5B 00 00 00 00 00 00 00 00 00 07 01 4F 00 00 00 00 00 00 00 00 00 00 00 00 00 00 00 00 00 00 00 01 00 01 07 00 2B
        //    Exceptions:
        //  Try           Handler
        //  Start  End    Start  End    Type                 
        //  -----  -----  -----  -----  ---------------------
        //  327    680    1384   3297   Ljava/lang/Throwable;
        //  327    680    1768   2008   Ljava/lang/Throwable;
        //  698    726    1624   1680   Ljava/lang/Throwable;
        //  726    739    872    907    Ljava/lang/Throwable;
        //  243    791    917    3319   Ljava/lang/Throwable;
        //  243    791    2080   2539   Ljava/lang/Throwable;
        //  809    837    1715   1768   Ljava/lang/Throwable;
        //  837    850    1680   1715   Ljava/lang/Throwable;
        //  196    872    2550   3167   Ljava/lang/Exception;
        // 
        // The error that occurred was:
        // 
        // java.lang.IndexOutOfBoundsException: Index 1079 out of bounds for length 1079
        //     at java.base/jdk.internal.util.Preconditions.outOfBounds(Preconditions.java:100)
        //     at java.base/jdk.internal.util.Preconditions.outOfBoundsCheckIndex(Preconditions.java:106)
        //     at java.base/jdk.internal.util.Preconditions.checkIndex(Preconditions.java:302)
        //     at java.base/java.util.Objects.checkIndex(Objects.java:385)
        //     at java.base/java.util.ArrayList.get(ArrayList.java:427)
        //     at com.strobel.decompiler.ast.AstBuilder.convertToAst(AstBuilder.java:3362)
        //     at com.strobel.decompiler.ast.AstBuilder.convertToAst(AstBuilder.java:3476)
        //     at com.strobel.decompiler.ast.AstBuilder.build(AstBuilder.java:112)
        //     at com.strobel.decompiler.languages.java.ast.AstMethodBodyBuilder.createMethodBody(AstMethodBodyBuilder.java:203)
        //     at com.strobel.decompiler.languages.java.ast.AstMethodBodyBuilder.createMethodBody(AstMethodBodyBuilder.java:93)
        //     at com.strobel.decompiler.languages.java.ast.AstBuilder.createMethodBody(AstBuilder.java:868)
        //     at com.strobel.decompiler.languages.java.ast.AstBuilder.createConstructor(AstBuilder.java:799)
        //     at com.strobel.decompiler.languages.java.ast.AstBuilder.addTypeMembers(AstBuilder.java:635)
        //     at com.strobel.decompiler.languages.java.ast.AstBuilder.createTypeCore(AstBuilder.java:605)
        //     at com.strobel.decompiler.languages.java.ast.AstBuilder.createTypeNoCache(AstBuilder.java:195)
        //     at com.strobel.decompiler.languages.java.ast.AstBuilder.createType(AstBuilder.java:162)
        //     at com.strobel.decompiler.languages.java.ast.AstBuilder.addType(AstBuilder.java:137)
        //     at com.strobel.decompiler.languages.java.JavaLanguage.buildAst(JavaLanguage.java:71)
        //     at com.strobel.decompiler.languages.java.JavaLanguage.decompileType(JavaLanguage.java:59)
        //     at com.strobel.decompiler.DecompilerDriver.decompileType(DecompilerDriver.java:334)
        //     at com.strobel.decompiler.DecompilerDriver.main(DecompilerDriver.java:148)
        // 
        throw new IllegalStateException("An error occurred while decompiling this method.");
    }
    
    @NotNull
    @Override
    protected Class<?> findClass(@NotNull final String name) {
        int n = 0xD22F6F8 ^ (0xA725F09 ^ 0x9A43472);
        Label_0499: {
            if (ogwwobatgayyjyld.widdxeioafyswjhq(n) == 2007297048) {
                n ^= 0x3C11ED92;
                Intrinsics.checkNotNullParameter((Object)name, siwjmvxjgv(dcqzpwblmulfssy(), jdqxmvovehalvyq(), n));
                if (ogwwobatgayyjyld.widdxeioafyswjhq(n) == -1758756727) {
                    final int n2 = 0x3BE0FD22 ^ n;
                    final byte[] array = this.classBytes.get(name);
                    Label_0424: {
                        if (array != null) {
                            if (ogwwobatgayyjyld.widdxeioafyswjhq(n2) != 1210870168) {
                                while (ogwwobatgayyjyld.widdxeioafyswjhq(n2) != 1210870168 || ogwwobatgayyjyld.widdxeioafyswjhq(n2) != (0x5185B1C6 ^ n2) || ogwwobatgayyjyld.widdxeioafyswjhq(n2) != 257181729 || ogwwobatgayyjyld.widdxeioafyswjhq(n2) != (0x49750408 ^ n2)) {}
                                throw new IllegalAccessException("double");
                            }
                            n = (0x10E829BB ^ n2);
                            final byte[] b = array;
                            if (ogwwobatgayyjyld.widdxeioafyswjhq(n) != -814930880) {
                                break Label_0499;
                            }
                            n ^= 0x6C26F5AD;
                            final byte b2 = (byte)(0x75CB5125 ^ n);
                            if (ogwwobatgayyjyld.widdxeioafyswjhq(n) == -1369798357) {
                                final int n3 = 0x21F58FA ^ n;
                                final Class<?> defineClass = this.defineClass(name, b, (byte)(0x77D409DF ^ n3), b.length);
                                Intrinsics.checkNotNullExpressionValue((Object)defineClass, siwjmvxjgv(yvwatjbddicczsy(), jdqxmvovehalvyq(), n3));
                                return defineClass;
                            }
                        }
                        else {
                            n = ojfurpnnjakpinoa(n2, 59388292);
                            if (ogwwobatgayyjyld.widdxeioafyswjhq(n) != 1417536952) {
                                if (ogwwobatgayyjyld.widdxeioafyswjhq(n) == 1417536952) {
                                    n = ojfurpnnjakpinoa(n, 728053171);
                                }
                                break Label_0499;
                            }
                            else {
                                Label_0356: {
                                Label_0348:
                                    while (true) {
                                        switch (ogwwobatgayyjyld.yphcfoidvruxcacx(n)) {
                                            case 2073893857: {
                                                continue;
                                            }
                                            case 74872621: {
                                                break Label_0348;
                                            }
                                            case 644250893: {
                                                break Label_0356;
                                            }
                                            default: {
                                                break Label_0424;
                                            }
                                        }
                                    }
                                    n ^= 0x6685AE83;
                                }
                                if (ogwwobatgayyjyld.widdxeioafyswjhq(n) == 1615892899) {
                                    final int n4 = 0x27EB22C5 ^ n;
                                    final Class<?> class1 = super.findClass(name);
                                    Intrinsics.checkNotNullExpressionValue((Object)class1, siwjmvxjgv(dwybzarzcewbdrz(), jdqxmvovehalvyq(), n4));
                                    return class1;
                                }
                                break Label_0499;
                            }
                        }
                    }
                    while (ogwwobatgayyjyld.widdxeioafyswjhq(n) != -1369798357 || ogwwobatgayyjyld.widdxeioafyswjhq(n) != (0x4AA03103 ^ n) || ogwwobatgayyjyld.widdxeioafyswjhq(n) != -1096790277 || ogwwobatgayyjyld.widdxeioafyswjhq(n) != (0xB892999 ^ n)) {}
                    throw new IllegalAccessException("double");
                }
            }
        }
        while (ogwwobatgayyjyld.widdxeioafyswjhq(n) != 1594460042 || ogwwobatgayyjyld.widdxeioafyswjhq(n) != (0x217C0FFC ^ n) || ogwwobatgayyjyld.widdxeioafyswjhq(n) != 1615892899 || ogwwobatgayyjyld.widdxeioafyswjhq(n) != (0x397081E6 ^ n) || ogwwobatgayyjyld.widdxeioafyswjhq(n) != 1417536952 || ogwwobatgayyjyld.widdxeioafyswjhq(n) != (0x71D1FC90 ^ n) || ogwwobatgayyjyld.widdxeioafyswjhq(n) != 2007297048 || ogwwobatgayyjyld.widdxeioafyswjhq(n) != (0x1F00E66F ^ n) || ogwwobatgayyjyld.widdxeioafyswjhq(n) != -814930880 || ogwwobatgayyjyld.widdxeioafyswjhq(n) != (0x64B213E1 ^ n) || ogwwobatgayyjyld.widdxeioafyswjhq(n) != -1758756727 || ogwwobatgayyjyld.widdxeioafyswjhq(n) != (0x2FF43272 ^ n)) {}
        throw new IllegalAccessException();
    }
    
    @NotNull
    public final Class<?> loadClassPublic(@NotNull final String name, final String s) {
        final int n = 0x457EE448 ^ (0x340B740A ^ 0x9A43472);
        if (ogwwobatgayyjyld.widdxeioafyswjhq(n) != -963829373) {
            while (ogwwobatgayyjyld.widdxeioafyswjhq(n) != -963829373 || ogwwobatgayyjyld.widdxeioafyswjhq(n) != (0x6816AD4F ^ n)) {}
            throw new IOException("double");
        }
        final int n2 = 0x72A5CFDE ^ n;
        Intrinsics.checkNotNullParameter((Object)name, siwjmvxjgv(zsyioohxxqynplb(), jdqxmvovehalvyq(), n2));
        if (ogwwobatgayyjyld.widdxeioafyswjhq(n2) == 1403215728) {
            final int n3 = 0x102651B6 ^ n2;
            final Class<?> loadClass = this.loadClass(name);
            Intrinsics.checkNotNullExpressionValue((Object)loadClass, siwjmvxjgv(tuvnatdfmpcqyvt(), jdqxmvovehalvyq(), n3));
            return loadClass;
        }
        while (ogwwobatgayyjyld.widdxeioafyswjhq(n2) != 1403215728 || ogwwobatgayyjyld.widdxeioafyswjhq(n2) != (0x7431D8BC ^ n2) || ogwwobatgayyjyld.widdxeioafyswjhq(n2) != -762195264 || ogwwobatgayyjyld.widdxeioafyswjhq(n2) != (0x2E14E601 ^ n2)) {}
        throw new RuntimeException();
    }
    
    static {
        (ByteClassLoader.nothing_to_see_here = new String[15])[0] = " \u2801\u287c\u280b\u2800\u28c6\u2800\u2800\u28f0\u28ff\u28eb\u28fe\u28bf\u28ff\u28ff\u280d\u28a0\u2820\u2800\u2800\u2880\u2830\u28be\u28fa\u28fb\u28ff\u28ff\u28ff\u28f7\u2840\u2800";
        ByteClassLoader.nothing_to_see_here[1] = "\u28e5\u2800\u2800\u2800\u2801\u2800\u2820\u28bb\u28ac\u2801\u28e0\u28fe\u281b\u2801\u2800\u2800\u2800\u2800\u2800\u2800\u2800\u2810\u2831\u280f\u2849\u2819\u28ff\u28ff\u2847\u2800";
        ByteClassLoader.nothing_to_see_here[2] = "\u28b3\u2800\u28b0\u2856\u2800\u2800\u2808\u2800\u28fa\u28b0\u28ff\u28bb\u28fe\u28f6\u28ff\u28ff\u28f6\u28f6\u28e4\u28e4\u28f4\u28fe\u28ff\u28f7\u28fc\u2846\u28b8\u28ff\u28e7\u2800";
        ByteClassLoader.nothing_to_see_here[3] = "\u2808\u2800\u281c\u2808\u28c0\u28d4\u28e6\u28a8\u28ff\u28ff\u28ff\u28fe\u28ff\u28ff\u28ff\u28ff\u28ff\u28ff\u28ff\u28ff\u28ff\u28ff\u28ff\u28ff\u28ff\u28c5\u28fc\u281b\u28b9\u2800";
        ByteClassLoader.nothing_to_see_here[4] = "\u2800\u2800\u2800\u2800\u288b\u287f\u287f\u28ef\u28ed\u285f\u28df\u28ff\u28ff\u28fd\u28ff\u28ff\u28ff\u28ff\u28ff\u28ff\u28ff\u28ff\u28ff\u28ff\u28ff\u28ff\u28ff\u2800\u2858\u2800";
        ByteClassLoader.nothing_to_see_here[5] = "\u2840\u2810\u2800\u2800\u2800\u28ff\u28ef\u287f\u28ff\u28ff\u28ff\u28ef\u28ff\u28ff\u28ff\u28ff\u28ff\u28ff\u28ff\u28ff\u28ff\u28ff\u287f\u280b\u28c9\u28bd\u28ff\u2846\u2800\u2800";
        ByteClassLoader.nothing_to_see_here[6] = "\u28b3\u2800\u2804\u2800\u2880\u28ff\u28ff\u28ff\u28ff\u28ff\u28ff\u28ff\u2819\u2809\u2809\u2809\u281b\u28fb\u289b\u28ff\u281b\u2803\u2800\u2810\u281b\u283b\u28ff\u2847\u2800\u2800";
        ByteClassLoader.nothing_to_see_here[7] = "\u28fe\u2804\u2800\u2800\u28b8\u28ff\u28ff\u287f\u281f\u281b\u2801\u2880\u2800\u2880\u2844\u28c0\u28e0\u28fe\u28ff\u28ff\u2860\u28f4\u28ce\u28c0\u28e0\u28e0\u28ff\u2847\u2800\u2800";
        ByteClassLoader.nothing_to_see_here[8] = "\u28e7\u2800\u28f4\u28c4\u28fd\u28ff\u28ff\u28ff\u28f6\u28f6\u28d6\u28f6\u28ec\u28fe\u28ff\u28fe\u28ff\u28ff\u28ff\u28ff\u28fd\u28ff\u28ff\u28ff\u28ff\u28ff\u28ff\u2847\u2800\u2800";
        ByteClassLoader.nothing_to_see_here[9] = "\u28ff\u28f6\u28c8\u286f\u28ff\u28ff\u28ff\u28ff\u28ff\u28ff\u28ff\u28ff\u28ff\u28ff\u287f\u280b\u28f9\u28a7\u28ff\u28ff\u28ff\u28c4\u2819\u28bf\u28ff\u28ff\u28ff\u2807\u2800\u2800";
        ByteClassLoader.nothing_to_see_here[10] = "\u2839\u28ff\u28ff\u28e7\u288c\u28bd\u28fb\u28bf\u28ef\u28ff\u28ff\u28ff\u28ff\u281f\u28e0\u2858\u283f\u281f\u281b\u281b\u281f\u281b\u28e7\u2848\u283b\u28fe\u28ff\u2800\u2800\u2800";
        ByteClassLoader.nothing_to_see_here[11] = "\u2800\u2808\u2809\u28f7\u287f\u28fd\u2836\u287e\u28bf\u28ff\u28ff\u28ff\u2883\u28e4\u28ff\u28f7\u28e4\u28e4\u28c4\u28c4\u28e0\u28fc\u287f\u28b7\u2880\u28ff\u284f\u2800\u2800\u2800";
        ByteClassLoader.nothing_to_see_here[12] = "\u2800\u2800\u2880\u28ff\u28f7\u280c\u28c8\u28cf\u28dd\u283d\u287f\u28f7\u28fe\u28cf\u28c0\u28c9\u28c9\u28c0\u28c0\u28c0\u28e0\u28e0\u28c4\u2878\u28fe\u28ff\u2803\u2800\u2800\u2800";
        ByteClassLoader.nothing_to_see_here[13] = "\u2800\u28f0\u287f\u28ff\u28e7\u2850\u2804\u2831\u28ff\u28fa\u28fd\u289f\u28ff\u28ff\u28bf\u28ff\u28cd\u2809\u2880\u28c0\u28d0\u28fc\u28ef\u2857\u281f\u284f\u2800\u2800\u2800\u2800";
        ByteClassLoader.nothing_to_see_here[14] = "\u28f0\u28ff\u2800\u28ff\u28ff\u28f4\u2840\u2802\u2818\u28b9\u28ed\u2842\u285a\u283f\u28bf\u28ff\u28ff\u28ff\u287f\u28bf\u28bf\u287f\u283f\u2881\u28f4\u28ff\u28f7\u28f6\u28e6\u28e4";
        ByteClassLoader.5raxzV3R39 = (0xA45D126E ^ new Random(-7323796922163264395L).nextInt());
    }
    
    public static String siwjmvxjgv(final byte[] bytes, final byte[] array, final int i) {
        final byte[] bytes2 = Integer.toString(i).getBytes();
        for (int j = 0; j < bytes.length; ++j) {
            final int n = j;
            bytes[n] ^= bytes2[j % bytes2.length];
            final int n2 = j;
            bytes[n2] ^= array[j % array.length];
        }
        return new String(bytes, StandardCharsets.UTF_16);
    }
    
    private static byte[] jdqxmvovehalvyq() {
        return new byte[] { 97, 20, 115, 9, 53, 103, 69, 27, 115, 78, 11, 13, 54, 115, 74, 61, 46, 23, 72, 125, 13, 40, 74, 32, 72, 116, 122, 40, 69, 86, 69, 4, 70, 24, 15, 38, 108, 16, 95, 42, 70, 59, 23, 60, 13, 83, 5, 66, 90, 9, 33, 97, 4, 115, 118, 24, 96, 4, 96, 57, 79, 63, 60, 49, 38, 29, 80, 126, 99, 103, 10, 104 };
    }
    
    private static byte[] dcqzpwblmulfssy() {
        return new byte[] { -89, -34, 64, 95, 12, 49, 119, 69, 64, 19 };
    }
    
    private static byte[] yvwatjbddicczsy() {
        return new byte[] { -83, -37, 66, 93, 6, 58, 113, 69, 69, 20, 57, 83, 7, 38, 121, 70, 26, 67, 126, 47, 63, 107, 123, 99, 123, 100, 78, 62, 115, 75, 119, 26, 119, 1 };
    }
    
    private static byte[] dwybzarzcewbdrz() {
        return new byte[] { -82, -39, 68, 92, 5, 58, 124, 70, 65, 19, 58, 124, 1, 44, 122, 104, 23, 87, 122, 55, 60, 50, 125, 61, 120, 110, 67, 53, 119, 70 };
    }
    
    private static byte[] tuvnatdfmpcqyvt() {
        return new byte[] { -85, -33, 66, 80, 12, 62, 112, 74, 71, 30, 63, 127, 3, 38, 124, 105, 30, 80, 124, 58, 60, 53, 115, 56, 125, 106, 78, 50, 113, 78 };
    }
    
    private static byte[] zsyioohxxqynplb() {
        return new byte[] { -82, -36, 70, 83, 5, 55, 124, 64, 69, 26 };
    }
    
    private static int ojfurpnnjakpinoa(final int n, final int n2) {
        return n ^ n2;
    }
}
